internet_search_bot/__init__.py
internet_search_bot/bot.py
my_project/__init__.py
my_project/main.py
gpity-0.1.3.dist-info/LICENSE
gpity-0.1.3.dist-info/METADATA
gpity-0.1.3.dist-info/WHEEL
gpity-0.1.3.dist-info/top_level.txt
gpity-0.1.3.dist-info/RECORD
