Metadata-Version: 2.2
Name: gpity
Version: 0.1.3
Classifier: Programming Language :: Python :: 3
Classifier: License :: OSI Approved :: MIT License
Classifier: Operating System :: OS Independent
Requires-Python: >=3.6
License-File: LICENSE
Requires-Dist: requests
Requires-Dist: deep-translator
Dynamic: classifier
Dynamic: requires-dist
Dynamic: requires-python
